{"polygon":"geojson/county_17.geojson","registered":"300666","code":"85BBDC91-AA5B-4985-BAB1-ED5E90EB448F","name":"MAKUENI","center":{"lat":-2.155226,"lon":37.787627},"status":"SUCCESS","region":{"location_type":"constituency","locations":[{"polygon":"geojson/constituency_85.geojson","registered":"42231","code":"8AECBE34-0F2B-437D-AA6B-078ACEA726DC","name":"KAITI","center":{"lat":-1.772546,"lon":37.438375}},{"polygon":"geojson/constituency_88.geojson","registered":"41252","code":"9FBA87A7-BD75-4A12-9DD1-AF81ED0504FB","name":"KIBWEZI EAST","center":{"lat":-2.607874,"lon":38.145065}},{"polygon":"geojson/constituency_87.geojson","registered":"56265","code":"0975B2B2-A923-4F9B-BAE3-D2B2B3A3A5FE","name":"KIBWEZI WEST","center":{"lat":-2.253424,"lon":37.804137}},{"polygon":"geojson/constituency_84.geojson","registered":"36204","code":"28BBC3B4-D13E-47DE-93BE-DA581882BAE5","name":"KILOME","center":{"lat":-1.845378,"lon":37.284105}},{"polygon":"geojson/constituency_86.geojson","registered":"64658","code":"B1400899-866A-4584-AEB9-7CD688CA1934","name":"MAKUENI","center":{"lat":-1.929547,"lon":37.711208}},{"polygon":"geojson/constituency_83.geojson","registered":"60220","code":"39A3DB74-1094-4368-947A-44B00C9A74C1","name":"MBOONI","center":{"lat":-1.65194,"lon":37.596311}}]}}