{"polygon":"geojson/constituency_64.geojson","registered":"66368","code":"13FEF90A-8183-4D27-8AB3-98FB33AF7DBB","name":"RUNYENJES","center":{"lat":-0.402893,"lon":37.561233},"status":"SUCCESS","region":{"location_type":"ward","locations":[{"polygon":"geojson/ward_319.geojson","registered":"11729","code":"9086D67E-0A2F-4730-96B4-8B06C58A9C3E","name":"CENTRAL  WARD","center":{"lat":-0.428956,"lon":37.572487}},{"polygon":"geojson/ward_317.geojson","registered":"10573","code":"4A939DBE-FFC4-43B0-8A98-91ED3BD69E78","name":"GATURI NORTH","center":{"lat":-0.428533,"lon":37.511646}},{"polygon":"geojson/ward_320.geojson","registered":"12345","code":"821997D8-39D6-4439-A7A3-F378C13A9545","name":"KAGAARI NORTH","center":{"lat":-0.326057,"lon":37.475043}},{"polygon":"geojson/ward_318.geojson","registered":"8987","code":"456FC2B1-1C52-4654-94F8-1CAB4B2F8F8A","name":"KAGAARI SOUTH","center":{"lat":-0.488389,"lon":37.611832}},{"polygon":"geojson/ward_321.geojson","registered":"10444","code":"52646EAE-B76D-4BE7-9149-43714F393BD8","name":"KYENI NORTH","center":{"lat":-0.339309,"lon":37.527898}},{"polygon":"geojson/ward_322.geojson","registered":"12280","code":"32125D31-DA33-48F1-8308-8F746270491B","name":"KYENI SOUTH","center":{"lat":-0.446733,"lon":37.649547}}]}}