{"polygon":"geojson/constituency_186.geojson","registered":"45523","code":"E85F327D-7318-43BC-A573-D9AD450588F9","name":"KAJIADO WEST","center":{"lat":-1.727718,"lon":36.388535},"status":"SUCCESS","region":{"location_type":"ward","locations":[{"polygon":"geojson/ward_929.geojson","registered":"10535","code":"1FDFA8AE-99C8-4029-9C6C-C48212777310","name":"EWUASO OoNKIDONG'I","center":{"lat":-1.33951,"lon":36.394632}},{"polygon":"geojson/ward_927.geojson","registered":"5606","code":"EFC637D8-53CB-4C79-9DB3-B29EAB71E780","name":"ILOODOKILANI","center":{"lat":-1.979908,"lon":36.495081}},{"polygon":"geojson/ward_926.geojson","registered":"19739","code":"994FC077-A7B1-4E1A-B795-33755141D495","name":"KEEKONYOKIE","center":{"lat":-1.600796,"lon":36.581315}},{"polygon":"geojson/ward_928.geojson","registered":"7264","code":"BE8BE792-1204-4D43-BEE2-4A47DC453477","name":"MAGADI","center":{"lat":-1.90883,"lon":36.209858}},{"polygon":"geojson/ward_930.geojson","registered":"2349","code":"F1D24879-A280-4CD6-A81F-9A7049BCDAD4","name":"MOSIRO","center":{"lat":-1.554608,"lon":36.182933}}]}}